{
	"class" : {
		"alphaVersion" : "EstebanLorenzano 5/12/2016 17:01:48",
		"commandName" : "EstebanLorenzano 5/12/2016 17:01:48",
		"description" : "EstebanLorenzano 5/12/2016 17:01:48",
		"generate" : "EstebanLorenzano 5/12/2016 17:01:48",
		"imageVersions" : "EstebanLorenzano 5/12/2016 17:01:48",
		"stableVersion" : "EstebanLorenzano 5/12/2016 17:01:48" },
	"instance" : {
		"activate" : "EstebanLorenzano 5/12/2016 17:01:48",
		"cleanUpAfterScript:" : "EstebanLorenzano 5/12/2016 17:01:48",
		"combinedScripts" : "EstebanLorenzano 5/12/2016 17:01:48",
		"defaultScript" : "EstebanLorenzano 5/12/2016 17:01:48",
		"ensureEmptyTestDirectory" : "EstebanLorenzano 5/12/2016 17:01:48",
		"generate:" : "EstebanLorenzano 5/12/2016 17:01:48",
		"generateScripts" : "EstebanLorenzano 5/12/2016 17:01:48",
		"imageScripts" : "EstebanLorenzano 5/12/2016 17:01:48",
		"imageVersions" : "EstebanLorenzano 5/12/2016 17:01:48",
		"indexScript" : "EstebanLorenzano 5/12/2016 17:01:48",
		"indexScriptExamplesHtmlOn:" : "EstebanLorenzano 5/12/2016 17:01:48",
		"minimalScripts" : "EstebanLorenzano 5/12/2016 17:01:48",
		"numericImageScripts" : "EstebanLorenzano 5/12/2016 17:01:48",
		"otherScriptsHtmlOn:" : "EstebanLorenzano 5/12/2016 17:01:48",
		"outputDirectory" : "EstebanLorenzano 5/12/2016 17:01:48",
		"printTestStartOfScript:" : "EstebanLorenzano 5/12/2016 17:01:48",
		"scripts" : "EstebanLorenzano 5/12/2016 17:01:48",
		"setScriptDirectory:" : "EstebanLorenzano 5/12/2016 17:01:48",
		"symbolicImageScripts" : "EstebanLorenzano 5/12/2016 17:01:48",
		"test:" : "EstebanLorenzano 5/12/2016 17:01:48",
		"testDirectory" : "EstebanLorenzano 5/12/2016 17:01:48",
		"testScripts" : "EstebanLorenzano 5/12/2016 17:01:48",
		"testTimeout" : "EstebanLorenzano 5/12/2016 17:01:48",
		"travisVmScripts" : "EstebanLorenzano 5/12/2016 17:01:48",
		"vmScripts" : "EstebanLorenzano 5/12/2016 17:01:48",
		"vmScriptsVersion:" : "EstebanLorenzano 5/12/2016 17:01:48" } }
