{
	"class" : {
		 },
	"instance" : {
		"artifactDescription" : "AndreiChis 4/5/2013 09:44",
		"defaultBasename" : "CamilloBruni 3/30/2013 15:08",
		"defaultVersion" : "EstebanLorenzano 3/25/2015 14:54",
		"description" : "CamilloBruni 5/17/2013 18:49",
		"generateBody" : "EstebanLorenzano 3/26/2015 11:55",
		"imageName" : "AndreiChis 4/5/2013 09:33",
		"imageUrl" : "CamilloBruni 3/30/2013 15:09",
		"imageZip" : "CamilloBruni 3/29/2013 18:08",
		"isImage" : "EstebanLorenzano 3/25/2015 16:18",
		"release" : "CamilloBruni 3/29/2013 18:05",
		"release:" : "CamilloBruni 3/29/2013 18:05",
		"version" : "EstebanLorenzano 3/25/2015 14:54",
		"version:" : "CamilloBruni 3/29/2013 18:06" } }
